wthings_gateway/__init__.py
wthings_gateway/wt_gateway.py
wthings_gateway/config/logs.conf
wthings_gateway/config/wt_gateway.yaml
wthings_gateway/connectors/__init__.py
wthings_gateway/connectors/connector.py
wthings_gateway/connectors/converter.py
wthings_gateway/connectors/ble/__init__.py
wthings_gateway/connectors/ble/ble_connector.py
wthings_gateway/connectors/ble/ble_uplink_converter.py
wthings_gateway/connectors/ble/bytes_ble_uplink_converter.py
wthings_gateway/connectors/modbus/__init__.py
wthings_gateway/connectors/modbus/bytes_modbus_downlink_converter.py
wthings_gateway/connectors/modbus/bytes_modbus_uplink_converter.py
wthings_gateway/connectors/modbus/modbus_connector.py
wthings_gateway/connectors/modbus/modbus_converter.py
wthings_gateway/connectors/mqtt/__init__.py
wthings_gateway/connectors/mqtt/json_mqtt_uplink_converter.py
wthings_gateway/connectors/mqtt/mqtt_connector.py
wthings_gateway/connectors/mqtt/mqtt_uplink_converter.py
wthings_gateway/connectors/opcua/__init__.py
wthings_gateway/connectors/opcua/opcua_connector.py
wthings_gateway/connectors/opcua/opcua_converter.py
wthings_gateway/connectors/opcua/opcua_uplink_converter.py
wthings_gateway/connectors/request/__init__.py
wthings_gateway/connectors/request/json_request_downlink_converter.py
wthings_gateway/connectors/request/json_request_uplink_converter.py
wthings_gateway/connectors/request/request_connector.py
wthings_gateway/connectors/request/request_converter.py
wthings_gateway/connectors/request/request_uplink_converter.py
wthings_gateway/extensions/__init__.py
wthings_gateway/extensions/ble/__init__.py
wthings_gateway/extensions/modbus/__init__.py
wthings_gateway/extensions/mqtt/__init__.py
wthings_gateway/extensions/mqtt/custom_mqtt_uplink_converter.py
wthings_gateway/extensions/opcua/__init__.py
wthings_gateway/extensions/request/__init__.py
wthings_gateway/extensions/request/custom_request_uplink_converter.py
wthings_gateway-2.1.0.9.dist-info/DESCRIPTION.rst
wthings_gateway-2.1.0.9.dist-info/METADATA
wthings_gateway-2.1.0.9.dist-info/RECORD
wthings_gateway-2.1.0.9.dist-info/WHEEL
wthings_gateway-2.1.0.9.dist-info/entry_points.txt
wthings_gateway-2.1.0.9.dist-info/metadata.json
wthings_gateway-2.1.0.9.dist-info/top_level.txt
