Metadata-Version: 2.0
Name: wthings-gateway
Version: 2.1.0.9
Summary: WThings Gateway for IoT devices.
Home-page: https://www.xiaobodata.com
Author: WThings
Author-email: xiaoboplus@visionet.com.cn
License: Apache Software License (Apache Software License 2.0)
Platform: UNKNOWN
Requires-Python: >=3.5
Requires-Dist: cffi
Requires-Dist: jsonpath-rw
Requires-Dist: regex
Requires-Dist: pip
Requires-Dist: jsonschema (==3.1.1)
Requires-Dist: lxml
Requires-Dist: opcua
Requires-Dist: paho-mqtt
Requires-Dist: pymodbus
Requires-Dist: Pyro4
Requires-Dist: pyserial
Requires-Dist: pytz
Requires-Dist: PyYAML
Requires-Dist: simplejson
Requires-Dist: pyrsistent
